rer.voltoplugin.search-1.0.2-py3.10-nspkg.pth
rer/voltoplugin/search/__init__.py
rer/voltoplugin/search/configure.zcml
rer/voltoplugin/search/interfaces.py
rer/voltoplugin/search/permissions.zcml
rer/voltoplugin/search/setuphandlers.py
rer/voltoplugin/search/testing.py
rer/voltoplugin/search/vocabularies.py
rer/voltoplugin/search/adapters/__init__.py
rer/voltoplugin/search/adapters/configure.zcml
rer/voltoplugin/search/adapters/custom_filters.py
rer/voltoplugin/search/browser/__init__.py
rer/voltoplugin/search/browser/configure.zcml
rer/voltoplugin/search/browser/controlpanel.py
rer/voltoplugin/search/locales/README.rst
rer/voltoplugin/search/locales/__init__.py
rer/voltoplugin/search/locales/rer.voltoplugin.search.pot
rer/voltoplugin/search/locales/update.py
rer/voltoplugin/search/locales/update.sh
rer/voltoplugin/search/locales/it/LC_MESSAGES/rer.voltoplugin.search.mo
rer/voltoplugin/search/locales/it/LC_MESSAGES/rer.voltoplugin.search.po
rer/voltoplugin/search/profiles/default/browserlayer.xml
rer/voltoplugin/search/profiles/default/catalog.xml
rer/voltoplugin/search/profiles/default/controlpanel.xml
rer/voltoplugin/search/profiles/default/metadata.xml
rer/voltoplugin/search/profiles/default/rolemap.xml
rer/voltoplugin/search/profiles/default/registry/main.xml
rer/voltoplugin/search/profiles/uninstall/browserlayer.xml
rer/voltoplugin/search/profiles/uninstall/controlpanel.xml
rer/voltoplugin/search/profiles/uninstall/registry.xml
rer/voltoplugin/search/restapi/__init__.py
rer/voltoplugin/search/restapi/configure.zcml
rer/voltoplugin/search/restapi/utils.py
rer/voltoplugin/search/restapi/controlpanel/__init__.py
rer/voltoplugin/search/restapi/controlpanel/configure.zcml
rer/voltoplugin/search/restapi/controlpanel/search_settings.py
rer/voltoplugin/search/restapi/serializer/__init__.py
rer/voltoplugin/search/restapi/serializer/catalog.py
rer/voltoplugin/search/restapi/serializer/configure.zcml
rer/voltoplugin/search/restapi/services/__init__.py
rer.voltoplugin.search-1.0.2.dist-info/LICENSE.GPL
rer.voltoplugin.search-1.0.2.dist-info/LICENSE.rst
rer.voltoplugin.search-1.0.2.dist-info/METADATA
rer.voltoplugin.search-1.0.2.dist-info/WHEEL
rer.voltoplugin.search-1.0.2.dist-info/entry_points.txt
rer.voltoplugin.search-1.0.2.dist-info/namespace_packages.txt
rer.voltoplugin.search-1.0.2.dist-info/top_level.txt
rer.voltoplugin.search-1.0.2.dist-info/RECORD
