Metadata-Version: 2.1
Name: rer.voltoplugin.search
Version: 1.0.2
Summary: Add-on RER for Plone to manage search results in Volto
Home-page: https://github.com/collective/rer.voltoplugin.search
Author: RedTurtle Technology
Author-email: sviluppo@redturtle.it
License: GPL version 2
Project-URL: PyPI, https://pypi.org/project/rer.voltoplugin.search/
Project-URL: Source, https://github.com/collective/rer.voltoplugin.search
Project-URL: Tracker, https://github.com/collective/rer.voltoplugin.search/issues
Keywords: Python Plone CMS
Classifier: Environment :: Web Environment
Classifier: Framework :: Plone
Classifier: Framework :: Plone :: Addon
Classifier: Framework :: Plone :: 6.0
Classifier: Programming Language :: Python
Classifier: Programming Language :: Python :: 3.8
Classifier: Programming Language :: Python :: 3.9
Classifier: Programming Language :: Python :: 3.10
Classifier: Operating System :: OS Independent
Classifier: License :: OSI Approved :: GNU General Public License v2 (GPLv2)
Classifier: Development Status :: 5 - Production/Stable
Requires-Python: >=3.8
License-File: LICENSE.GPL
License-File: LICENSE.rst
Requires-Dist: setuptools
Requires-Dist: plone.api >=1.8.4
Provides-Extra: test
Requires-Dist: gocept.pytestlayer ; extra == 'test'
Requires-Dist: plone.app.testing ; extra == 'test'
Requires-Dist: plone.restapi[test] ; extra == 'test'
Requires-Dist: pytest-cov ; extra == 'test'
Requires-Dist: pytest-plone >=0.2.0 ; extra == 'test'
Requires-Dist: pytest-docker ; extra == 'test'
Requires-Dist: pytest-mock ; extra == 'test'
Requires-Dist: pytest ; extra == 'test'
Requires-Dist: zest.releaser[recommended] ; extra == 'test'
Requires-Dist: zestreleaser.towncrier ; extra == 'test'
Requires-Dist: requests-mock ; extra == 'test'
